amw_theme/__init__.py
amw_theme/globaltoc.html
amw_theme/layout.html
amw_theme/snippets.py
amw_theme/theme.conf
amw_theme/components/dark_mode_toggle.html
amw_theme/components/notification_banner.html
amw_theme/components/source_link.html
amw_theme/static/basic_mod.css
amw_theme/static/basic_mod.css.map
amw_theme/static/fonts/roboto/LICENSE.txt
amw_theme/static/fonts/roboto/roboto-bold.woff2
amw_theme/static/fonts/roboto/roboto-italic.woff2
amw_theme/static/fonts/roboto/roboto.woff2
amw_theme/static/fonts/roboto-mono/LICENSE.txt
amw_theme/static/fonts/roboto-mono/roboto-mono-bold-italic.woff2
amw_theme/static/fonts/roboto-mono/roboto-mono-bold.woff2
amw_theme/static/fonts/roboto-mono/roboto-mono-italic.woff2
amw_theme/static/fonts/roboto-mono/roboto-mono.woff2
amw_theme/static/js/petite-vue.js
amw_theme/static/js/theme.js
amw_theme-0.18.2.dist-info/LICENSE
amw_theme-0.18.2.dist-info/METADATA
amw_theme-0.18.2.dist-info/WHEEL
amw_theme-0.18.2.dist-info/entry_points.txt
amw_theme-0.18.2.dist-info/top_level.txt
amw_theme-0.18.2.dist-info/RECORD
